{"start":"2019-08-26T01:04:59.286Z","end":"2019-08-26T01:05:04.854Z","capabilities":{"applicationCacheEnabled":false,"rotatable":false,"mobileEmulationEnabled":false,"networkConnectionEnabled":false,"chrome":{"chromedriverVersion":"2.26.436421 (6c1a3ab469ad86fd49c8d97ede4a6b96a49ca5f6)","userDataDir":"/var/folders/p7/6ymv7981107c8f230k6pr_zw0000gp/T/.org.chromium.Chromium.oiFlyX"},"takesHeapSnapshot":true,"pageLoadStrategy":"normal","databaseEnabled":false,"handlesAlerts":true,"hasTouchScreen":false,"version":"53.0.2785.89","platform":"MAC","browserConnectionEnabled":false,"nativeEvents":true,"acceptSslCerts":true,"webdriver.remote.sessionid":"f9c765e3d663a1402ed645c3e8ebff2636ad6db4","locationContextEnabled":true,"webStorageEnabled":true,"browserName":"chrome","takesScreenshot":true,"javascriptEnabled":true,"cssSelectorsEnabled":true,"unexpectedAlertBehaviour":""},"host":"hub-cloud.browserstack.com","port":443,"baseUrl":"http://noreferrer.hypnosphi.de","framework":"mocha","mochaOpts":{"timeout":300000,"ui":"bdd"},"suites":[{"name":"window.opener","duration":4274,"start":"2019-08-26T01:04:59.899Z","end":"2019-08-26T01:05:04.173Z","sessionId":"f9c765e3d663a1402ed645c3e8ebff2636ad6db4","tests":[{"name":"should be null on a fresh page","start":"2019-08-26T01:04:59.901Z","end":"2019-08-26T01:05:00.528Z","duration":627,"state":"passed"},{"name":"should be present after clicking a link with rel=\"opener\"","start":"2019-08-26T01:05:00.529Z","end":"2019-08-26T01:05:01.631Z","duration":1102,"state":"passed"},{"name":"should be null after clicking a link with rel=\"noreferrer noopener\"","start":"2019-08-26T01:05:01.632Z","end":"2019-08-26T01:05:02.805Z","duration":1173,"state":"passed"},{"name":"should be null after clicking a link with rel=\"noreferrer\"","start":"2019-08-26T01:05:02.806Z","end":"2019-08-26T01:05:04.172Z","duration":1366,"state":"passed"}],"hooks":[{"start":"2019-08-26T01:04:59.902Z","end":"2019-08-26T01:04:59.903Z","duration":1,"title":"\"before each\" hook","associatedSuite":"","state":"passed"},{"start":"2019-08-26T01:05:00.529Z","end":"2019-08-26T01:05:00.529Z","duration":0,"title":"\"after each\" hook","associatedSuite":"","state":"passed"},{"start":"2019-08-26T01:05:00.529Z","end":"2019-08-26T01:05:00.530Z","duration":1,"title":"\"before each\" hook","associatedSuite":"","state":"passed"},{"start":"2019-08-26T01:05:01.631Z","end":"2019-08-26T01:05:01.632Z","duration":1,"title":"\"after each\" hook","associatedSuite":"","state":"passed"},{"start":"2019-08-26T01:05:01.632Z","end":"2019-08-26T01:05:01.632Z","duration":0,"title":"\"before each\" hook","associatedSuite":"","state":"passed"},{"start":"2019-08-26T01:05:02.806Z","end":"2019-08-26T01:05:02.806Z","duration":0,"title":"\"after each\" hook","associatedSuite":"","state":"passed"},{"start":"2019-08-26T01:05:02.806Z","end":"2019-08-26T01:05:02.806Z","duration":0,"title":"\"before each\" hook","associatedSuite":"","state":"passed"},{"start":"2019-08-26T01:05:04.172Z","end":"2019-08-26T01:05:04.172Z","duration":0,"title":"\"after each\" hook","associatedSuite":"","state":"passed"}]}],"specs":["/Users/jetbrains/no-referrer-test/test.js"],"state":{"passed":4,"failed":0,"skipped":0}}