{"start":"2019-08-26T01:50:14.034Z","end":"2019-08-26T01:50:19.484Z","capabilities":{"mobileEmulationEnabled":false,"timeouts":{"implicit":0,"pageLoad":300000,"script":30000},"hasTouchScreen":false,"platform":"MAC","acceptSslCerts":false,"goog:chromeOptions":{"debuggerAddress":"localhost:57586"},"acceptInsecureCerts":false,"webStorageEnabled":true,"browserName":"chrome","takesScreenshot":true,"javascriptEnabled":true,"setWindowRect":true,"unexpectedAlertBehaviour":"ignore","applicationCacheEnabled":false,"rotatable":false,"networkConnectionEnabled":false,"chrome":{"chromedriverVersion":"75.0.3770.140 (2d9f97485c7b07dc18a74666574f19176731995c-refs/branch-heads/3770@{#1155})","userDataDir":"/var/folders/yj/h3bj394n2tn74bp3vdngj35c0000jy/T/.com.google.Chrome.VSqs5k"},"takesHeapSnapshot":true,"pageLoadStrategy":"normal","strictFileInteractability":false,"databaseEnabled":false,"handlesAlerts":true,"version":"75.0.3770.80","browserConnectionEnabled":false,"nativeEvents":true,"webdriver.remote.sessionid":"ef050c962d2c9e6a866c7e0aba0c793b28d31514","locationContextEnabled":true,"cssSelectorsEnabled":true},"host":"hub-cloud.browserstack.com","port":443,"baseUrl":"http://noreferrer.hypnosphi.de","framework":"mocha","mochaOpts":{"timeout":300000,"ui":"bdd"},"suites":[{"name":"window.opener","duration":4198,"start":"2019-08-26T01:50:14.544Z","end":"2019-08-26T01:50:18.742Z","sessionId":"ef050c962d2c9e6a866c7e0aba0c793b28d31514","tests":[{"name":"should be null on a fresh page","start":"2019-08-26T01:50:14.545Z","end":"2019-08-26T01:50:14.957Z","duration":412,"state":"passed"},{"name":"should be present after clicking a link with rel=\"opener\"","start":"2019-08-26T01:50:14.958Z","end":"2019-08-26T01:50:16.162Z","duration":1204,"state":"passed"},{"name":"should be null after clicking a link with rel=\"noreferrer noopener\"","start":"2019-08-26T01:50:16.162Z","end":"2019-08-26T01:50:17.343Z","duration":1181,"state":"passed"},{"name":"should be null after clicking a link with rel=\"noreferrer\"","start":"2019-08-26T01:50:17.343Z","end":"2019-08-26T01:50:18.741Z","duration":1398,"state":"passed"}],"hooks":[{"start":"2019-08-26T01:50:14.545Z","end":"2019-08-26T01:50:14.546Z","duration":1,"title":"\"before each\" hook","associatedSuite":"","state":"passed"},{"start":"2019-08-26T01:50:14.957Z","end":"2019-08-26T01:50:14.958Z","duration":1,"title":"\"after each\" hook","associatedSuite":"","state":"passed"},{"start":"2019-08-26T01:50:14.958Z","end":"2019-08-26T01:50:14.958Z","duration":0,"title":"\"before each\" hook","associatedSuite":"","state":"passed"},{"start":"2019-08-26T01:50:16.162Z","end":"2019-08-26T01:50:16.162Z","duration":0,"title":"\"after each\" hook","associatedSuite":"","state":"passed"},{"start":"2019-08-26T01:50:16.162Z","end":"2019-08-26T01:50:16.163Z","duration":1,"title":"\"before each\" hook","associatedSuite":"","state":"passed"},{"start":"2019-08-26T01:50:17.343Z","end":"2019-08-26T01:50:17.343Z","duration":0,"title":"\"after each\" hook","associatedSuite":"","state":"passed"},{"start":"2019-08-26T01:50:17.343Z","end":"2019-08-26T01:50:17.343Z","duration":0,"title":"\"before each\" hook","associatedSuite":"","state":"passed"},{"start":"2019-08-26T01:50:18.741Z","end":"2019-08-26T01:50:18.741Z","duration":0,"title":"\"after each\" hook","associatedSuite":"","state":"passed"}]}],"specs":["/Users/jetbrains/no-referrer-test/test.js"],"state":{"passed":4,"failed":0,"skipped":0}}