{"start":"2019-08-26T01:16:22.752Z","end":"2019-08-26T01:16:28.202Z","capabilities":{"applicationCacheEnabled":false,"rotatable":false,"mobileEmulationEnabled":false,"networkConnectionEnabled":false,"chrome":{"chromedriverVersion":"2.28.455517 (2c6d2707d8ea850c862f04ac066724273981e88f)","userDataDir":"/var/folders/9n/t5vj6z6j5wqdvghr_ztt8cxr0000kf/T/.org.chromium.Chromium.rqqdHt"},"takesHeapSnapshot":true,"pageLoadStrategy":"normal","databaseEnabled":false,"handlesAlerts":true,"hasTouchScreen":false,"version":"55.0.2883.75","platform":"MAC","browserConnectionEnabled":false,"nativeEvents":true,"acceptSslCerts":true,"webdriver.remote.sessionid":"3199d158fb6ccc8176f05df323dcf10ccc7de41b","locationContextEnabled":true,"webStorageEnabled":true,"browserName":"chrome","takesScreenshot":true,"javascriptEnabled":true,"cssSelectorsEnabled":true,"unexpectedAlertBehaviour":""},"host":"hub-cloud.browserstack.com","port":443,"baseUrl":"http://noreferrer.hypnosphi.de","framework":"mocha","mochaOpts":{"timeout":300000,"ui":"bdd"},"suites":[{"name":"window.opener","duration":4190,"start":"2019-08-26T01:16:23.328Z","end":"2019-08-26T01:16:27.518Z","sessionId":"3199d158fb6ccc8176f05df323dcf10ccc7de41b","tests":[{"name":"should be null on a fresh page","start":"2019-08-26T01:16:23.329Z","end":"2019-08-26T01:16:23.878Z","duration":549,"state":"passed"},{"name":"should be present after clicking a link with rel=\"opener\"","start":"2019-08-26T01:16:23.879Z","end":"2019-08-26T01:16:24.982Z","duration":1103,"state":"passed"},{"name":"should be null after clicking a link with rel=\"noreferrer noopener\"","start":"2019-08-26T01:16:24.983Z","end":"2019-08-26T01:16:25.977Z","duration":994,"state":"passed"},{"name":"should be null after clicking a link with rel=\"noreferrer\"","start":"2019-08-26T01:16:25.978Z","end":"2019-08-26T01:16:27.517Z","duration":1539,"state":"passed"}],"hooks":[{"start":"2019-08-26T01:16:23.329Z","end":"2019-08-26T01:16:23.330Z","duration":1,"title":"\"before each\" hook","associatedSuite":"","state":"passed"},{"start":"2019-08-26T01:16:23.879Z","end":"2019-08-26T01:16:23.879Z","duration":0,"title":"\"after each\" hook","associatedSuite":"","state":"passed"},{"start":"2019-08-26T01:16:23.879Z","end":"2019-08-26T01:16:23.879Z","duration":0,"title":"\"before each\" hook","associatedSuite":"","state":"passed"},{"start":"2019-08-26T01:16:24.983Z","end":"2019-08-26T01:16:24.983Z","duration":0,"title":"\"after each\" hook","associatedSuite":"","state":"passed"},{"start":"2019-08-26T01:16:24.983Z","end":"2019-08-26T01:16:24.983Z","duration":0,"title":"\"before each\" hook","associatedSuite":"","state":"passed"},{"start":"2019-08-26T01:16:25.978Z","end":"2019-08-26T01:16:25.978Z","duration":0,"title":"\"after each\" hook","associatedSuite":"","state":"passed"},{"start":"2019-08-26T01:16:25.978Z","end":"2019-08-26T01:16:25.978Z","duration":0,"title":"\"before each\" hook","associatedSuite":"","state":"passed"},{"start":"2019-08-26T01:16:27.517Z","end":"2019-08-26T01:16:27.517Z","duration":0,"title":"\"after each\" hook","associatedSuite":"","state":"passed"}]}],"specs":["/Users/jetbrains/no-referrer-test/test.js"],"state":{"passed":4,"failed":0,"skipped":0}}