{"start":"2019-08-26T01:06:23.815Z","end":"2019-08-26T01:06:29.869Z","capabilities":{"applicationCacheEnabled":false,"rotatable":false,"chrome":{"userDataDir":"/var/folders/c7/vllh81zs7fb80hnm7ky437mc0000gq/T/.org.chromium.Chromium.ixYxCX"},"takesHeapSnapshot":true,"databaseEnabled":false,"handlesAlerts":true,"version":"32.0.1700.102","platform":"MAC","browserConnectionEnabled":false,"nativeEvents":true,"acceptSslCerts":true,"webdriver.remote.sessionid":"d050aff133224926e92fb57ad630ff998311ba24","locationContextEnabled":true,"webStorageEnabled":true,"browserName":"chrome","takesScreenshot":true,"javascriptEnabled":true,"cssSelectorsEnabled":true},"host":"hub-cloud.browserstack.com","port":443,"baseUrl":"http://noreferrer.hypnosphi.de","framework":"mocha","mochaOpts":{"timeout":300000,"ui":"bdd"},"suites":[{"name":"window.opener","duration":4850,"start":"2019-08-26T01:06:24.338Z","end":"2019-08-26T01:06:29.188Z","sessionId":"d050aff133224926e92fb57ad630ff998311ba24","tests":[{"name":"should be null on a fresh page","start":"2019-08-26T01:06:24.340Z","end":"2019-08-26T01:06:24.913Z","duration":573,"state":"passed"},{"name":"should be present after clicking a link with rel=\"opener\"","start":"2019-08-26T01:06:24.914Z","end":"2019-08-26T01:06:26.209Z","duration":1295,"state":"passed"},{"name":"should be null after clicking a link with rel=\"noreferrer noopener\"","start":"2019-08-26T01:06:26.209Z","end":"2019-08-26T01:06:27.687Z","duration":1478,"state":"passed"},{"name":"should be null after clicking a link with rel=\"noreferrer\"","start":"2019-08-26T01:06:27.687Z","end":"2019-08-26T01:06:29.187Z","duration":1500,"state":"passed"}],"hooks":[{"start":"2019-08-26T01:06:24.340Z","end":"2019-08-26T01:06:24.342Z","duration":2,"title":"\"before each\" hook","associatedSuite":"","state":"passed"},{"start":"2019-08-26T01:06:24.913Z","end":"2019-08-26T01:06:24.914Z","duration":1,"title":"\"after each\" hook","associatedSuite":"","state":"passed"},{"start":"2019-08-26T01:06:24.914Z","end":"2019-08-26T01:06:24.914Z","duration":0,"title":"\"before each\" hook","associatedSuite":"","state":"passed"},{"start":"2019-08-26T01:06:26.209Z","end":"2019-08-26T01:06:26.209Z","duration":0,"title":"\"after each\" hook","associatedSuite":"","state":"passed"},{"start":"2019-08-26T01:06:26.209Z","end":"2019-08-26T01:06:26.209Z","duration":0,"title":"\"before each\" hook","associatedSuite":"","state":"passed"},{"start":"2019-08-26T01:06:27.687Z","end":"2019-08-26T01:06:27.687Z","duration":0,"title":"\"after each\" hook","associatedSuite":"","state":"passed"},{"start":"2019-08-26T01:06:27.687Z","end":"2019-08-26T01:06:27.687Z","duration":0,"title":"\"before each\" hook","associatedSuite":"","state":"passed"},{"start":"2019-08-26T01:06:29.188Z","end":"2019-08-26T01:06:29.188Z","duration":0,"title":"\"after each\" hook","associatedSuite":"","state":"passed"}]}],"specs":["/Users/jetbrains/no-referrer-test/test.js"],"state":{"passed":4,"failed":0,"skipped":0}}