{"start":"2019-08-26T01:14:53.196Z","end":"2019-08-26T01:14:58.794Z","capabilities":{"applicationCacheEnabled":false,"rotatable":false,"databaseEnabled":false,"handlesAlerts":true,"version":"24.0.1312.52","platform":"MAC","browserConnectionEnabled":false,"nativeEvents":true,"acceptSslCerts":false,"webdriver.remote.sessionid":"88dab422cf7721902478193b64ed7a5e268be0b7","locationContextEnabled":true,"webStorageEnabled":true,"browserName":"chrome","takesScreenshot":true,"chrome.chromedriverVersion":"26.0.1383.0","javascriptEnabled":true,"cssSelectorsEnabled":true},"host":"hub-cloud.browserstack.com","port":443,"baseUrl":"http://noreferrer.hypnosphi.de","framework":"mocha","mochaOpts":{"timeout":300000,"ui":"bdd"},"suites":[{"name":"window.opener","duration":4241,"start":"2019-08-26T01:14:53.722Z","end":"2019-08-26T01:14:57.963Z","sessionId":"88dab422cf7721902478193b64ed7a5e268be0b7","tests":[{"name":"should be null on a fresh page","start":"2019-08-26T01:14:53.723Z","end":"2019-08-26T01:14:54.046Z","duration":323,"state":"passed"},{"name":"should be present after clicking a link with rel=\"opener\"","start":"2019-08-26T01:14:54.046Z","end":"2019-08-26T01:14:55.094Z","duration":1048,"state":"passed"},{"name":"should be null after clicking a link with rel=\"noreferrer noopener\"","start":"2019-08-26T01:14:55.095Z","end":"2019-08-26T01:14:56.569Z","duration":1474,"state":"passed"},{"name":"should be null after clicking a link with rel=\"noreferrer\"","start":"2019-08-26T01:14:56.569Z","end":"2019-08-26T01:14:57.962Z","duration":1393,"state":"passed"}],"hooks":[{"start":"2019-08-26T01:14:53.723Z","end":"2019-08-26T01:14:53.724Z","duration":1,"title":"\"before each\" hook","associatedSuite":"","state":"passed"},{"start":"2019-08-26T01:14:54.046Z","end":"2019-08-26T01:14:54.046Z","duration":0,"title":"\"after each\" hook","associatedSuite":"","state":"passed"},{"start":"2019-08-26T01:14:54.047Z","end":"2019-08-26T01:14:54.047Z","duration":0,"title":"\"before each\" hook","associatedSuite":"","state":"passed"},{"start":"2019-08-26T01:14:55.095Z","end":"2019-08-26T01:14:55.095Z","duration":0,"title":"\"after each\" hook","associatedSuite":"","state":"passed"},{"start":"2019-08-26T01:14:55.095Z","end":"2019-08-26T01:14:55.095Z","duration":0,"title":"\"before each\" hook","associatedSuite":"","state":"passed"},{"start":"2019-08-26T01:14:56.569Z","end":"2019-08-26T01:14:56.569Z","duration":0,"title":"\"after each\" hook","associatedSuite":"","state":"passed"},{"start":"2019-08-26T01:14:56.569Z","end":"2019-08-26T01:14:56.569Z","duration":0,"title":"\"before each\" hook","associatedSuite":"","state":"passed"},{"start":"2019-08-26T01:14:57.962Z","end":"2019-08-26T01:14:57.962Z","duration":0,"title":"\"after each\" hook","associatedSuite":"","state":"passed"}]}],"specs":["/Users/jetbrains/no-referrer-test/test.js"],"state":{"passed":4,"failed":0,"skipped":0}}