{"start":"2019-08-26T01:51:29.717Z","end":"2019-08-26T01:51:36.192Z","capabilities":{"applicationCacheEnabled":false,"rotatable":false,"handlesAlerts":true,"databaseEnabled":true,"version":"22.0","platform":"MAC","browserConnectionEnabled":true,"nativeEvents":false,"acceptSslCerts":false,"webdriver.remote.sessionid":"94647ddad302446eeb9af77fd5c64bd040466a5f","webStorageEnabled":true,"locationContextEnabled":true,"browserName":"firefox","takesScreenshot":true,"javascriptEnabled":true,"cssSelectorsEnabled":true},"host":"hub-cloud.browserstack.com","port":443,"baseUrl":"http://noreferrer.hypnosphi.de","framework":"mocha","mochaOpts":{"timeout":300000,"ui":"bdd"},"suites":[{"name":"window.opener","duration":4800,"start":"2019-08-26T01:51:30.371Z","end":"2019-08-26T01:51:35.171Z","sessionId":"94647ddad302446eeb9af77fd5c64bd040466a5f","tests":[{"name":"should be null on a fresh page","start":"2019-08-26T01:51:30.372Z","end":"2019-08-26T01:51:30.567Z","duration":195,"state":"passed"},{"name":"should be present after clicking a link with rel=\"opener\"","start":"2019-08-26T01:51:30.568Z","end":"2019-08-26T01:51:31.911Z","duration":1343,"state":"passed"},{"name":"should be null after clicking a link with rel=\"noreferrer noopener\"","start":"2019-08-26T01:51:31.912Z","end":"2019-08-26T01:51:33.527Z","duration":1615,"state":"failed","errorType":"AssertionError","error":"expected true to equal false","standardError":"AssertionError: expected true to equal false\n    at Context.it (/Users/jetbrains/no-referrer-test/test.js:38:26)\n    at process._tickCallback (internal/process/next_tick.js:68:7)"},{"name":"should be null after clicking a link with rel=\"noreferrer\"","start":"2019-08-26T01:51:33.527Z","end":"2019-08-26T01:51:35.170Z","duration":1643,"state":"failed","errorType":"AssertionError","error":"expected true to equal false","standardError":"AssertionError: expected true to equal false\n    at Context.it (/Users/jetbrains/no-referrer-test/test.js:38:26)\n    at process._tickCallback (internal/process/next_tick.js:68:7)"}],"hooks":[{"start":"2019-08-26T01:51:30.372Z","end":"2019-08-26T01:51:30.373Z","duration":1,"title":"\"before each\" hook","associatedSuite":"","state":"passed"},{"start":"2019-08-26T01:51:30.568Z","end":"2019-08-26T01:51:30.568Z","duration":0,"title":"\"after each\" hook","associatedSuite":"","state":"passed"},{"start":"2019-08-26T01:51:30.568Z","end":"2019-08-26T01:51:30.568Z","duration":0,"title":"\"before each\" hook","associatedSuite":"","state":"passed"},{"start":"2019-08-26T01:51:31.912Z","end":"2019-08-26T01:51:31.912Z","duration":0,"title":"\"after each\" hook","associatedSuite":"","state":"passed"},{"start":"2019-08-26T01:51:31.912Z","end":"2019-08-26T01:51:31.912Z","duration":0,"title":"\"before each\" hook","associatedSuite":"","state":"passed"},{"start":"2019-08-26T01:51:33.527Z","end":"2019-08-26T01:51:33.527Z","duration":0,"title":"\"after each\" hook","associatedSuite":"","state":"passed"},{"start":"2019-08-26T01:51:33.528Z","end":"2019-08-26T01:51:33.528Z","duration":0,"title":"\"before each\" hook","associatedSuite":"","state":"passed"},{"start":"2019-08-26T01:51:35.170Z","end":"2019-08-26T01:51:35.170Z","duration":0,"title":"\"after each\" hook","associatedSuite":"","state":"passed"}]}],"specs":["/Users/jetbrains/no-referrer-test/test.js"],"state":{"passed":2,"failed":2,"skipped":0}}