{"start":"2019-08-26T01:53:12.531Z","end":"2019-08-26T01:53:20.504Z","capabilities":{"applicationCacheEnabled":false,"rotatable":false,"handlesAlerts":true,"databaseEnabled":true,"version":"41.0","platform":"MAC","nativeEvents":false,"acceptSslCerts":false,"webdriver.remote.sessionid":"0066d73eea5740f0eecdf348070a4c570f901b2d","webStorageEnabled":true,"locationContextEnabled":true,"browserName":"firefox","takesScreenshot":true,"javascriptEnabled":true,"cssSelectorsEnabled":true},"host":"hub-cloud.browserstack.com","port":443,"baseUrl":"http://noreferrer.hypnosphi.de","framework":"mocha","mochaOpts":{"timeout":300000,"ui":"bdd"},"suites":[{"name":"window.opener","duration":6660,"start":"2019-08-26T01:53:13.089Z","end":"2019-08-26T01:53:19.749Z","sessionId":"0066d73eea5740f0eecdf348070a4c570f901b2d","tests":[{"name":"should be null on a fresh page","start":"2019-08-26T01:53:13.090Z","end":"2019-08-26T01:53:13.367Z","duration":277,"state":"passed"},{"name":"should be present after clicking a link with rel=\"opener\"","start":"2019-08-26T01:53:13.368Z","end":"2019-08-26T01:53:15.318Z","duration":1950,"state":"passed"},{"name":"should be null after clicking a link with rel=\"noreferrer noopener\"","start":"2019-08-26T01:53:15.318Z","end":"2019-08-26T01:53:17.404Z","duration":2086,"state":"passed"},{"name":"should be null after clicking a link with rel=\"noreferrer\"","start":"2019-08-26T01:53:17.405Z","end":"2019-08-26T01:53:19.748Z","duration":2343,"state":"passed"}],"hooks":[{"start":"2019-08-26T01:53:13.090Z","end":"2019-08-26T01:53:13.091Z","duration":1,"title":"\"before each\" hook","associatedSuite":"","state":"passed"},{"start":"2019-08-26T01:53:13.367Z","end":"2019-08-26T01:53:13.368Z","duration":1,"title":"\"after each\" hook","associatedSuite":"","state":"passed"},{"start":"2019-08-26T01:53:13.368Z","end":"2019-08-26T01:53:13.368Z","duration":0,"title":"\"before each\" hook","associatedSuite":"","state":"passed"},{"start":"2019-08-26T01:53:15.318Z","end":"2019-08-26T01:53:15.318Z","duration":0,"title":"\"after each\" hook","associatedSuite":"","state":"passed"},{"start":"2019-08-26T01:53:15.319Z","end":"2019-08-26T01:53:15.319Z","duration":0,"title":"\"before each\" hook","associatedSuite":"","state":"passed"},{"start":"2019-08-26T01:53:17.404Z","end":"2019-08-26T01:53:17.405Z","duration":1,"title":"\"after each\" hook","associatedSuite":"","state":"passed"},{"start":"2019-08-26T01:53:17.405Z","end":"2019-08-26T01:53:17.405Z","duration":0,"title":"\"before each\" hook","associatedSuite":"","state":"passed"},{"start":"2019-08-26T01:53:19.748Z","end":"2019-08-26T01:53:19.749Z","duration":1,"title":"\"after each\" hook","associatedSuite":"","state":"passed"}]}],"specs":["/Users/jetbrains/no-referrer-test/test.js"],"state":{"passed":4,"failed":0,"skipped":0}}