{"start":"2019-08-26T01:18:19.753Z","end":"2019-08-26T01:18:26.716Z","capabilities":{"applicationCacheEnabled":false,"rotatable":false,"handlesAlerts":true,"databaseEnabled":true,"version":"47.0.1","platform":"MAC","nativeEvents":false,"acceptSslCerts":false,"webdriver.remote.sessionid":"1e01967e23a593753f5c45c1b3c21d53cafbc6ac","webStorageEnabled":true,"locationContextEnabled":true,"browserName":"firefox","takesScreenshot":true,"javascriptEnabled":true,"cssSelectorsEnabled":true},"host":"hub-cloud.browserstack.com","port":443,"baseUrl":"http://noreferrer.hypnosphi.de","framework":"mocha","mochaOpts":{"timeout":300000,"ui":"bdd"},"suites":[{"name":"window.opener","duration":5852,"start":"2019-08-26T01:18:20.266Z","end":"2019-08-26T01:18:26.118Z","sessionId":"1e01967e23a593753f5c45c1b3c21d53cafbc6ac","tests":[{"name":"should be null on a fresh page","start":"2019-08-26T01:18:20.267Z","end":"2019-08-26T01:18:20.565Z","duration":298,"state":"passed"},{"name":"should be present after clicking a link with rel=\"opener\"","start":"2019-08-26T01:18:20.566Z","end":"2019-08-26T01:18:22.351Z","duration":1785,"state":"passed"},{"name":"should be null after clicking a link with rel=\"noreferrer noopener\"","start":"2019-08-26T01:18:22.352Z","end":"2019-08-26T01:18:24.092Z","duration":1740,"state":"passed"},{"name":"should be null after clicking a link with rel=\"noreferrer\"","start":"2019-08-26T01:18:24.093Z","end":"2019-08-26T01:18:26.117Z","duration":2024,"state":"passed"}],"hooks":[{"start":"2019-08-26T01:18:20.267Z","end":"2019-08-26T01:18:20.267Z","duration":0,"title":"\"before each\" hook","associatedSuite":"","state":"passed"},{"start":"2019-08-26T01:18:20.565Z","end":"2019-08-26T01:18:20.566Z","duration":1,"title":"\"after each\" hook","associatedSuite":"","state":"passed"},{"start":"2019-08-26T01:18:20.566Z","end":"2019-08-26T01:18:20.566Z","duration":0,"title":"\"before each\" hook","associatedSuite":"","state":"passed"},{"start":"2019-08-26T01:18:22.351Z","end":"2019-08-26T01:18:22.351Z","duration":0,"title":"\"after each\" hook","associatedSuite":"","state":"passed"},{"start":"2019-08-26T01:18:22.352Z","end":"2019-08-26T01:18:22.352Z","duration":0,"title":"\"before each\" hook","associatedSuite":"","state":"passed"},{"start":"2019-08-26T01:18:24.092Z","end":"2019-08-26T01:18:24.093Z","duration":1,"title":"\"after each\" hook","associatedSuite":"","state":"passed"},{"start":"2019-08-26T01:18:24.093Z","end":"2019-08-26T01:18:24.093Z","duration":0,"title":"\"before each\" hook","associatedSuite":"","state":"passed"},{"start":"2019-08-26T01:18:26.117Z","end":"2019-08-26T01:18:26.117Z","duration":0,"title":"\"after each\" hook","associatedSuite":"","state":"passed"}]}],"specs":["/Users/jetbrains/no-referrer-test/test.js"],"state":{"passed":4,"failed":0,"skipped":0}}