{"start":"2019-08-26T01:54:42.675Z","end":"2019-08-26T01:54:48.930Z","capabilities":{"moz:profile":"/var/folders/yj/h3bj394n2tn74bp3vdngj35c0000jy/T/rust_mozprofile.jo1cffK0b7LC","rotatable":false,"timeouts":{"implicit":0,"pageLoad":300000,"script":30000},"pageLoadStrategy":"normal","platform":"ANY","specificationLevel":0,"moz:accessibilityChecks":false,"webdriver.remote.sessionid":"7a56e83c9e8c53a68d730c2c2a5712ae6ddcd197","acceptInsecureCerts":false,"browserVersion":"53.0","platformVersion":"17.7.0","moz:processID":48992,"browserName":"firefox","takesScreenshot":true,"javascriptEnabled":true,"platformName":"darwin","cssSelectorsEnabled":true},"host":"hub-cloud.browserstack.com","port":443,"baseUrl":"http://noreferrer.hypnosphi.de","framework":"mocha","mochaOpts":{"timeout":300000,"ui":"bdd"},"suites":[{"name":"window.opener","duration":5074,"start":"2019-08-26T01:54:43.200Z","end":"2019-08-26T01:54:48.274Z","sessionId":"7a56e83c9e8c53a68d730c2c2a5712ae6ddcd197","tests":[{"name":"should be null on a fresh page","start":"2019-08-26T01:54:43.201Z","end":"2019-08-26T01:54:43.489Z","duration":288,"state":"passed"},{"name":"should be present after clicking a link with rel=\"opener\"","start":"2019-08-26T01:54:43.490Z","end":"2019-08-26T01:54:45.041Z","duration":1551,"state":"passed"},{"name":"should be null after clicking a link with rel=\"noreferrer noopener\"","start":"2019-08-26T01:54:45.042Z","end":"2019-08-26T01:54:46.528Z","duration":1486,"state":"passed"},{"name":"should be null after clicking a link with rel=\"noreferrer\"","start":"2019-08-26T01:54:46.529Z","end":"2019-08-26T01:54:48.273Z","duration":1744,"state":"passed"}],"hooks":[{"start":"2019-08-26T01:54:43.201Z","end":"2019-08-26T01:54:43.201Z","duration":0,"title":"\"before each\" hook","associatedSuite":"","state":"passed"},{"start":"2019-08-26T01:54:43.489Z","end":"2019-08-26T01:54:43.490Z","duration":1,"title":"\"after each\" hook","associatedSuite":"","state":"passed"},{"start":"2019-08-26T01:54:43.490Z","end":"2019-08-26T01:54:43.490Z","duration":0,"title":"\"before each\" hook","associatedSuite":"","state":"passed"},{"start":"2019-08-26T01:54:45.042Z","end":"2019-08-26T01:54:45.042Z","duration":0,"title":"\"after each\" hook","associatedSuite":"","state":"passed"},{"start":"2019-08-26T01:54:45.042Z","end":"2019-08-26T01:54:45.042Z","duration":0,"title":"\"before each\" hook","associatedSuite":"","state":"passed"},{"start":"2019-08-26T01:54:46.529Z","end":"2019-08-26T01:54:46.529Z","duration":0,"title":"\"after each\" hook","associatedSuite":"","state":"passed"},{"start":"2019-08-26T01:54:46.529Z","end":"2019-08-26T01:54:46.529Z","duration":0,"title":"\"before each\" hook","associatedSuite":"","state":"passed"},{"start":"2019-08-26T01:54:48.273Z","end":"2019-08-26T01:54:48.273Z","duration":0,"title":"\"after each\" hook","associatedSuite":"","state":"passed"}]}],"specs":["/Users/jetbrains/no-referrer-test/test.js"],"state":{"passed":4,"failed":0,"skipped":0}}