{"start":"2019-08-26T01:27:26.279Z","end":"2019-08-26T01:27:31.997Z","capabilities":{"moz:profile":"C:\\Windows\\proxy\\rust_mozprofile.izBLoT9HWGoh","rotatable":false,"timeouts":{"implicit":0,"page load":300000,"script":30000},"pageLoadStrategy":"normal","platform":"ANY","specificationLevel":0,"moz:accessibilityChecks":false,"webdriver.remote.sessionid":"2d459770302b305bcc11d2f6adc5764a5cfa634d","acceptInsecureCerts":false,"browserVersion":"52.0","platformVersion":"10.0","moz:processID":10764,"browserName":"firefox","takesScreenshot":true,"javascriptEnabled":true,"platformName":"windows_nt","cssSelectorsEnabled":true},"host":"hub-cloud.browserstack.com","port":443,"baseUrl":"http://noreferrer.hypnosphi.de","framework":"mocha","mochaOpts":{"timeout":300000,"ui":"bdd"},"suites":[{"name":"window.opener","duration":4622,"start":"2019-08-26T01:27:26.786Z","end":"2019-08-26T01:27:31.408Z","sessionId":"2d459770302b305bcc11d2f6adc5764a5cfa634d","tests":[{"name":"should be null on a fresh page","start":"2019-08-26T01:27:26.787Z","end":"2019-08-26T01:27:27.110Z","duration":323,"state":"passed"},{"name":"should be present after clicking a link with rel=\"opener\"","start":"2019-08-26T01:27:27.110Z","end":"2019-08-26T01:27:28.420Z","duration":1310,"state":"passed"},{"name":"should be null after clicking a link with rel=\"noreferrer noopener\"","start":"2019-08-26T01:27:28.420Z","end":"2019-08-26T01:27:29.797Z","duration":1377,"state":"passed"},{"name":"should be null after clicking a link with rel=\"noreferrer\"","start":"2019-08-26T01:27:29.797Z","end":"2019-08-26T01:27:31.408Z","duration":1611,"state":"passed"}],"hooks":[{"start":"2019-08-26T01:27:26.787Z","end":"2019-08-26T01:27:26.788Z","duration":1,"title":"\"before each\" hook","associatedSuite":"","state":"passed"},{"start":"2019-08-26T01:27:27.110Z","end":"2019-08-26T01:27:27.110Z","duration":0,"title":"\"after each\" hook","associatedSuite":"","state":"passed"},{"start":"2019-08-26T01:27:27.111Z","end":"2019-08-26T01:27:27.111Z","duration":0,"title":"\"before each\" hook","associatedSuite":"","state":"passed"},{"start":"2019-08-26T01:27:28.420Z","end":"2019-08-26T01:27:28.420Z","duration":0,"title":"\"after each\" hook","associatedSuite":"","state":"passed"},{"start":"2019-08-26T01:27:28.420Z","end":"2019-08-26T01:27:28.420Z","duration":0,"title":"\"before each\" hook","associatedSuite":"","state":"passed"},{"start":"2019-08-26T01:27:29.797Z","end":"2019-08-26T01:27:29.797Z","duration":0,"title":"\"after each\" hook","associatedSuite":"","state":"passed"},{"start":"2019-08-26T01:27:29.797Z","end":"2019-08-26T01:27:29.797Z","duration":0,"title":"\"before each\" hook","associatedSuite":"","state":"passed"},{"start":"2019-08-26T01:27:31.408Z","end":"2019-08-26T01:27:31.408Z","duration":0,"title":"\"after each\" hook","associatedSuite":"","state":"passed"}]}],"specs":["/Users/jetbrains/no-referrer-test/test.js"],"state":{"passed":4,"failed":0,"skipped":0}}