{"start":"2019-08-26T01:41:22.612Z","end":"2019-08-26T01:41:28.352Z","capabilities":{"moz:profile":"C:\\Windows\\proxy\\rust_mozprofile.pVGp7SmN3Wyb","rotatable":false,"moz:geckodriverVersion":"0.24.0","timeouts":{"implicit":0,"pageLoad":300000,"script":30000},"pageLoadStrategy":"normal","unhandledPromptBehavior":"dismiss and notify","strictFileInteractability":false,"moz:headless":false,"moz:accessibilityChecks":false,"moz:useNonSpecCompliantPointerOrigin":false,"acceptInsecureCerts":false,"browserVersion":"68.0","moz:shutdownTimeout":60000,"platformVersion":"6.2","moz:processID":2696,"browserName":"firefox","moz:buildID":"20190705220548","platformName":"windows","setWindowRect":true,"moz:webdriverClick":true,"webdriver.remote.sessionid":"584f1610ea07910441ceb2b8b41451729b98ccd9"},"host":"hub-cloud.browserstack.com","port":443,"baseUrl":"http://noreferrer.hypnosphi.de","framework":"mocha","mochaOpts":{"timeout":300000,"ui":"bdd"},"suites":[{"name":"window.opener","duration":3751,"start":"2019-08-26T01:41:23.161Z","end":"2019-08-26T01:41:26.912Z","sessionId":"584f1610ea07910441ceb2b8b41451729b98ccd9","tests":[{"name":"should be null on a fresh page","start":"2019-08-26T01:41:23.161Z","end":"2019-08-26T01:41:23.343Z","duration":182,"state":"passed"},{"name":"should be present after clicking a link with rel=\"opener\"","start":"2019-08-26T01:41:23.344Z","end":"2019-08-26T01:41:24.807Z","duration":1463,"state":"passed"},{"name":"should be null after clicking a link with rel=\"noreferrer noopener\"","start":"2019-08-26T01:41:24.808Z","end":"2019-08-26T01:41:25.764Z","duration":956,"state":"passed"},{"name":"should be null after clicking a link with rel=\"noreferrer\"","start":"2019-08-26T01:41:25.764Z","end":"2019-08-26T01:41:26.911Z","duration":1147,"state":"passed"}],"hooks":[{"start":"2019-08-26T01:41:23.162Z","end":"2019-08-26T01:41:23.162Z","duration":0,"title":"\"before each\" hook","associatedSuite":"","state":"passed"},{"start":"2019-08-26T01:41:23.344Z","end":"2019-08-26T01:41:23.344Z","duration":0,"title":"\"after each\" hook","associatedSuite":"","state":"passed"},{"start":"2019-08-26T01:41:23.344Z","end":"2019-08-26T01:41:23.344Z","duration":0,"title":"\"before each\" hook","associatedSuite":"","state":"passed"},{"start":"2019-08-26T01:41:24.808Z","end":"2019-08-26T01:41:24.808Z","duration":0,"title":"\"after each\" hook","associatedSuite":"","state":"passed"},{"start":"2019-08-26T01:41:24.808Z","end":"2019-08-26T01:41:24.808Z","duration":0,"title":"\"before each\" hook","associatedSuite":"","state":"passed"},{"start":"2019-08-26T01:41:25.764Z","end":"2019-08-26T01:41:25.764Z","duration":0,"title":"\"after each\" hook","associatedSuite":"","state":"passed"},{"start":"2019-08-26T01:41:25.765Z","end":"2019-08-26T01:41:25.765Z","duration":0,"title":"\"before each\" hook","associatedSuite":"","state":"passed"},{"start":"2019-08-26T01:41:26.912Z","end":"2019-08-26T01:41:26.912Z","duration":0,"title":"\"after each\" hook","associatedSuite":"","state":"passed"}]}],"specs":["/Users/jetbrains/no-referrer-test/test.js"],"state":{"passed":4,"failed":0,"skipped":0}}