{"start":"2019-08-26T01:17:22.811Z","end":"2019-08-26T01:17:29.559Z","capabilities":{"applicationCacheEnabled":false,"rotatable":false,"handlesAlerts":true,"databaseEnabled":true,"version":"43.0","platform":"MAC","nativeEvents":false,"acceptSslCerts":false,"webdriver.remote.sessionid":"56c7cbb48337953202039af1a06e97216a912a5f","webStorageEnabled":true,"locationContextEnabled":true,"browserName":"firefox","takesScreenshot":true,"javascriptEnabled":true,"cssSelectorsEnabled":true},"host":"hub-cloud.browserstack.com","port":443,"baseUrl":"http://noreferrer.hypnosphi.de","framework":"mocha","mochaOpts":{"timeout":300000,"ui":"bdd"},"suites":[{"name":"window.opener","duration":5320,"start":"2019-08-26T01:17:23.398Z","end":"2019-08-26T01:17:28.718Z","sessionId":"56c7cbb48337953202039af1a06e97216a912a5f","tests":[{"name":"should be null on a fresh page","start":"2019-08-26T01:17:23.399Z","end":"2019-08-26T01:17:23.668Z","duration":269,"state":"passed"},{"name":"should be present after clicking a link with rel=\"opener\"","start":"2019-08-26T01:17:23.668Z","end":"2019-08-26T01:17:25.245Z","duration":1577,"state":"passed"},{"name":"should be null after clicking a link with rel=\"noreferrer noopener\"","start":"2019-08-26T01:17:25.245Z","end":"2019-08-26T01:17:26.842Z","duration":1597,"state":"passed"},{"name":"should be null after clicking a link with rel=\"noreferrer\"","start":"2019-08-26T01:17:26.842Z","end":"2019-08-26T01:17:28.717Z","duration":1875,"state":"passed"}],"hooks":[{"start":"2019-08-26T01:17:23.399Z","end":"2019-08-26T01:17:23.400Z","duration":1,"title":"\"before each\" hook","associatedSuite":"","state":"passed"},{"start":"2019-08-26T01:17:23.668Z","end":"2019-08-26T01:17:23.668Z","duration":0,"title":"\"after each\" hook","associatedSuite":"","state":"passed"},{"start":"2019-08-26T01:17:23.668Z","end":"2019-08-26T01:17:23.668Z","duration":0,"title":"\"before each\" hook","associatedSuite":"","state":"passed"},{"start":"2019-08-26T01:17:25.245Z","end":"2019-08-26T01:17:25.245Z","duration":0,"title":"\"after each\" hook","associatedSuite":"","state":"passed"},{"start":"2019-08-26T01:17:25.245Z","end":"2019-08-26T01:17:25.245Z","duration":0,"title":"\"before each\" hook","associatedSuite":"","state":"passed"},{"start":"2019-08-26T01:17:26.842Z","end":"2019-08-26T01:17:26.842Z","duration":0,"title":"\"after each\" hook","associatedSuite":"","state":"passed"},{"start":"2019-08-26T01:17:26.842Z","end":"2019-08-26T01:17:26.842Z","duration":0,"title":"\"before each\" hook","associatedSuite":"","state":"passed"},{"start":"2019-08-26T01:17:28.717Z","end":"2019-08-26T01:17:28.718Z","duration":1,"title":"\"after each\" hook","associatedSuite":"","state":"passed"}]}],"specs":["/Users/jetbrains/no-referrer-test/test.js"],"state":{"passed":4,"failed":0,"skipped":0}}